ign_pdal_tools-1.15.8.dist-info/licenses/LICENSE.md
pdaltools/_version.py
pdaltools/add_points_in_pointcloud.py
pdaltools/color.py
pdaltools/create_random_laz.py
pdaltools/download_image.py
pdaltools/las_add_buffer.py
pdaltools/las_clip.py
pdaltools/las_comparison.py
pdaltools/las_info.py
pdaltools/las_merge.py
pdaltools/las_remove_dimensions.py
pdaltools/las_rename_dimension.py
pdaltools/pcd_info.py
pdaltools/replace_area_in_pointcloud.py
pdaltools/replace_attribute_in_las.py
pdaltools/standardize_format.py
pdaltools/unlock_file.py
ign_pdal_tools-1.15.8.dist-info/METADATA
ign_pdal_tools-1.15.8.dist-info/WHEEL
ign_pdal_tools-1.15.8.dist-info/top_level.txt
ign_pdal_tools-1.15.8.dist-info/RECORD
