Metadata-Version: 2.4
Name: ign-pdal-tools
Version: 1.15.8
Summary: Library for common LAS files manipulation with PDAL
Author-email: Guillaume Liegard <guillaume.liegard@ign.fr>
License-File: LICENSE.md
Dynamic: license-file
